[{
   "number": "1",
   "mizobible": "amaherawhchu, amah chu êngah a awm angin keini pawh ênga awm kan nih chuan, kan inpâwl tlâng a; tin, a Fapa Isua thisenin kan sual zawng zawng min tlen faisak ṭhîn a ni.",
   "bunglehchang": "1 JOHANA 1:7 MIZOVBSI"
},
{ 
   "number": "2",
   "mizobible": "Chutichuan, kan Lalpa Isua Krista Pathian leh a Pa chu, thinlung hmun khat leh inthuruala kan chawimawi theihna tûrin, chhelna leh thlamuanna Pathian chuan, Krista Isua sawi angin rilru hmun khat pu tawnin awmtîr che u rawh se.",
   "bunglehchang": "ROM 15:5‭-‬6 MIZOVBSI" 
},
{ 
   "number": "3",
   "mizobible": "Lalpa anga thianghlim hi an awm lo; Nangmah ang rêng an awm si lo, Kan Pathian ang lungpui rêng a awm hek lo.",
   "bunglehchang": "1 SAMUELA 2:2 MIZOVBSI" 
},
{ 
   "number": "4",
   "mizobible": "₹₹",
   "bunglehchang": "##" 
},
{ 
   "number": "5",
   "mizobible": "₹₹",
   "bunglehchang": "##" 
},
{ 
   "number": "6",
   "mizobible": "₹₹",
   "bunglehchang": "##" 
},
{ 
   "number": "7",
   "mizobible": "₹₹",
   "bunglehchang": "##" 
},
{ 
   "number": "8",
   "mizobible": "₹₹",
   "bunglehchang": "##" 
},
{ 
   "number": "9",
   "mizobible": "₹₹",
   "bunglehchang": "##" 
},
{ 
   "number": "10",
   "mizobible": "₹₹",
   "bunglehchang": "##" 
},
{ 
   "number": "11",
   "mizobible": "₹₹",
   "bunglehchang": "##" 
},
{ 
   "number": "12",
   "mizobible": "₹₹",
   "bunglehchang": "##" 
},
{ 
   "number": "13",
   "mizobible": "₹₹",
   "bunglehchang": "##" 
},
{ 
   "number": "14",
   "mizobible": "₹₹",
   "bunglehchang": "##" 
},
{ 
   "number": "15",
   "mizobible": "₹₹",
   "bunglehchang": "##" 
},
{ 
   "number": "16",
   "mizobible": "₹₹",
   "bunglehchang": "##" 
},
{ 
   "number": "17",
   "mizobible": "₹₹",
   "bunglehchang": "##" 
},
{ 
   "number": "18",
   "mizobible": "₹₹",
   "bunglehchang": "##" 
},
{ 
   "number": "19",
   "mizobible": "₹₹",
   "bunglehchang": "##" 
},
{ 
   "number": "20",
   "mizobible": "₹₹",
   "bunglehchang": "##" 
},
{ 
   "number": "21",
   "mizobible": "₹₹",
   "bunglehchang": "##" 
},
{ 
   "number": "22",
   "mizobible": "₹₹",
   "bunglehchang": "##" 
},
{ 
   "number": "23",
   "mizobible": "₹₹",
   "bunglehchang": "##" 
},
{ 
   "number": "24",
   "mizobible": "₹₹",
   "bunglehchang": "##" 
},
{ 
   "number": "25",
   "mizobible": "₹₹",
   "bunglehchang": "##" 
},
{ 
   "number": "26",
   "mizobible": "₹₹",
   "bunglehchang": "##" 
},
{ 
   "number": "27",
   "mizobible": "₹₹",
   "bunglehchang": "##" 
},
{ 
   "number": "28",
   "mizobible": "₹₹",
   "bunglehchang": "##" 
},
{ 
   "number": "29",
   "mizobible": "₹₹",
   "bunglehchang": "##" 
},
{ 
   "number": "30",
   "mizobible": "₹₹",
   "bunglehchang": "##" 
},
{ 
   "number": "31",
   "mizobible": "₹₹",
   "bunglehchang": "##" 
},
{ 
   "number": "32",
   "mizobible": "₹₹",
   "bunglehchang": "##" 
},
{ 
   "number": "33",
   "mizobible": "₹₹",
   "bunglehchang": "##" 
},
{ 
   "number": "34",
   "mizobible": "₹₹",
   "bunglehchang": "##" 
},
{ 
   "number": "35",
   "mizobible": "₹₹",
   "bunglehchang": "##" 
},
{ 
   "number": "36",
   "mizobible": "₹₹",
   "bunglehchang": "##" 
},
{ 
   "number": "37",
   "mizobible": "₹₹",
   "bunglehchang": "##" 
},
{ 
   "number": "37",
   "mizobible": "₹₹",
   "bunglehchang": "##" 
},
{ 
   "number": "38",
   "mizobible": "₹₹",
   "bunglehchang": "##" 
},
{ 
   "number": "39",
   "mizobible": "₹₹",
   "bunglehchang": "##" 
},
{ 
   "number": "40",
   "mizobible": "₹₹",
   "bunglehchang": "##" 
},
{ 
   "number": "41",
   "mizobible": "₹₹",
   "bunglehchang": "##" 
},
{ 
   "number": "42",
   "mizobible": "₹₹",
   "bunglehchang": "##" 
},
{ 
   "number": "43",
   "mizobible": "₹₹",
   "bunglehchang": "##" 
},
{ 
   "number": "44",
   "mizobible": "₹₹",
   "bunglehchang": "##" 
},
{ 
   "number": "45",
   "mizobible": "₹₹",
   "bunglehchang": "##" 
},
{ 
   "number": "46",
   "mizobible": "₹₹",
   "bunglehchang": "##" 
},
{ 
   "number": "47",
   "mizobible": "₹₹",
   "bunglehchang": "##" 
},
{ 
   "number": "48",
   "mizobible": "₹₹",
   "bunglehchang": "##" 
},
{ 
   "number": "49",
   "mizobible": "₹₹",
   "bunglehchang": "##" 
},
{ 
   "number": "50",
   "mizobible": "₹₹",
   "bunglehchang": "##" 
},
{ 
   "number": "51",
   "mizobible": "₹₹",
   "bunglehchang": "##" 
},
{ 
   "number": "52",
   "mizobible": "₹₹",
   "bunglehchang": "##" 
},
{ 
   "number": "53",
   "mizobible": "₹₹",
   "bunglehchang": "##" 
},
{ 
   "number": "54",
   "mizobible": "₹₹",
   "bunglehchang": "##" 
},
{ 
   "number": "55",
   "mizobible": "₹₹",
   "bunglehchang": "##" 
},
{ 
   "number": "56",
   "mizobible": "₹₹",
   "bunglehchang": "##" 
},
{ 
   "number": "57",
   "mizobible": "₹₹",
   "bunglehchang": "##" 
},
{ 
   "number": "58",
   "mizobible": "₹₹",
   "bunglehchang": "##" 
},
{ 
   "number": "59",
   "mizobible": "₹₹",
   "bunglehchang": "##" 
},
{ 
   "number": "60",
   "mizobible": "₹₹",
   "bunglehchang": "##" 
},
{ 
   "number": "61",
   "mizobible": "₹₹",
   "bunglehchang": "##" 
},
{ 
   "number": "62",
   "mizobible": "₹₹",
   "bunglehchang": "##" 
},
{ 
   "number": "63",
   "mizobible": "₹₹",
   "bunglehchang": "##" 
},
{ 
   "number": "64",
   "mizobible": "₹₹",
   "bunglehchang": "##" 
},
{ 
   "number": "65",
   "mizobible": "₹₹",
   "bunglehchang": "##" 
},
{ 
   "number": "66",
   "mizobible": "₹₹",
   "bunglehchang": "##" 
},
{ 
   "number": "67",
   "mizobible": "₹₹",
   "bunglehchang": "##" 
},
{ 
   "number": "68",
   "mizobible": "₹₹",
   "bunglehchang": "##" 
},
{ 
   "number": "69",
   "mizobible": "₹₹",
   "bunglehchang": "##" 
},
{ 
   "number": "70",
   "mizobible": "₹₹",
   "bunglehchang": "##" 
},
{ 
   "number": "71",
   "mizobible": "₹₹",
   "bunglehchang": "##" 
},
{ 
   "number": "72",
   "mizobible": "₹₹",
   "bunglehchang": "##" 
},
{ 
   "number": "73",
   "mizobible": "₹₹",
   "bunglehchang": "##" 
},
{ 
   "number": "74",
   "mizobible": "₹₹",
   "bunglehchang": "##" 
},
{ 
   "number": "75",
   "mizobible": "₹₹",
   "bunglehchang": "##" 
},
{ 
   "number": "76",
   "mizobible": "₹₹",
   "bunglehchang": "##" 
},
{ 
   "number": "77",
   "mizobible": "₹₹",
   "bunglehchang": "##" 
},
{ 
   "number": "78",
   "mizobible": "₹₹",
   "bunglehchang": "##" 
},
{ 
   "number": "79",
   "mizobible": "₹₹",
   "bunglehchang": "##" 
},
{ 
   "number": "80",
   "mizobible": "₹₹",
   "bunglehchang": "##" 
},
{ 
   "number": "81",
   "mizobible": "₹₹",
   "bunglehchang": "##" 
},
{ 
   "number": "82",
   "mizobible": "₹₹",
   "bunglehchang": "##" 
},
{ 
   "number": "83",
   "mizobible": "₹₹",
   "bunglehchang": "##" 
},
{ 
   "number": "84",
   "mizobible": "₹₹",
   "bunglehchang": "##" 
},
{ 
   "number": "85",
   "mizobible": "₹₹",
   "bunglehchang": "##" 
},
{ 
   "number": "86",
   "mizobible": "₹₹",
   "bunglehchang": "##" 
},
{ 
   "number": "87",
   "mizobible": "₹₹",
   "bunglehchang": "##" 
},
{ 
   "number": "88",
   "mizobible": "₹₹",
   "bunglehchang": "##" 
},
{ 
   "number": "89",
   "mizobible": "₹₹",
   "bunglehchang": "##" 
},
{ 
   "number": "90",
   "mizobible": "₹₹",
   "bunglehchang": "##" 
},
{ 
   "number": "91",
   "mizobible": "₹₹",
   "bunglehchang": "##" 
},
{ 
   "number": "92",
   "mizobible": "₹₹",
   "bunglehchang": "##" 
},
{ 
   "number": "93",
   "mizobible": "₹₹",
   "bunglehchang": "##" 
},
{ 
   "number": "94",
   "mizobible": "₹₹",
   "bunglehchang": "##" 
},
{ 
   "number": "95",
   "mizobible": "₹₹",
   "bunglehchang": "##" 
},
{ 
   "number": "96",
   "mizobible": "₹₹",
   "bunglehchang": "##" 
},
{ 
   "number": "97",
   "mizobible": "₹₹",
   "bunglehchang": "##" 
},
{ 
   "number": "98",
   "mizobible": "₹₹",
   "bunglehchang": "##" 
},
{ 
   "number": "99",
   "mizobible": "₹₹",
   "bunglehchang": "##" 
},
{ 
   "number": "100",
   "mizobible": "₹₹",
   "bunglehchang": "##" 
}]